mongos/__init__.py
mongos/_fields.py
mongos/_manager.py
pbt_mongo-1.0.0.dist-info/WHEEL
pbt_mongo-1.0.0.dist-info/METADATA
pbt_mongo-1.0.0.dist-info/RECORD
