Metadata-Version: 2.1
Name: pbt-mongo
Version: 1.0.0
Summary: Mongo driver
Author: everhide
Author-email: i.tolkachnikov@gmail.com
Requires-Python: >=3.9,<4.0
Classifier: Programming Language :: Python :: 3
Classifier: Programming Language :: Python :: 3.10
Classifier: Programming Language :: Python :: 3.9
Requires-Dist: motor (>=3.0.0,<4.0.0)
